[{"name":"lanozdriver","paname":{ "Ботанічний сад імені Миколи Гришка" : "100352601", "Парк «Нивки»" : "378507377", "Парк «Інтернаціональний»" : "37853135", "Бабин Яр" : "630779811", "Парк КПІ" : "23707909", "Парк «Юність»" : "37853135", "Хрещатий парк" : "30356317", "Парк «Інтернаціональний»" : "37568873", "Печерський ландшафтний парк" : "30914703", "Парк Шевченка" : "444883195", "Парк Шевченка" : "23581536", "Наводницький парк" : "30914703", "Ботанічний сад НУБіП України" : "497414885", "Печерський ландшафтний парк" : "23709143", "Державний меморіал «Биківнянські могили»" : "613952682", "Відрадний" : "32608259", "Сирецький гай" : "-8885198", "Ботанічний сад імені Олександра Фоміна" : "256474904", "Ботанічний сад імені Олександра Фоміна" : "444883195", "Парк КПІ" : "-4138136", "Парк Перемоги" : "23705293", "Парк «Нивки»" : "-4178379", "Бабин Яр" : "-3967863", "Сирецький Гай" : "-8885211", "парк Кіото" : "-4683243", "Сирецький Гай" : "-5637222", "Національний природний парк «Голосіївський»" : "497414885", "бульвар" : "444883195", "Кирилівський гай" : "630779811", "Національний природний парк «Голосіївський»" : "-1652168" },"count":34086},{"name":"velmyshanovnyi","paname":{ "Кирилівський гай" : "630779811", "Хрещатий парк" : "30356317", "Печерський ландшафтний парк" : "23709143", "Бабин Яр" : "-3967863", "Наводницький парк" : "30914703", "Національний природний парк «Голосіївський»" : "-1652168", "Бабин Яр" : "630779811", "Печерський ландшафтний парк" : "30914703", "Ботанічний сад імені Миколи Гришка" : "100352601" },"count":15229},{"name":"yaroslavwave","paname":{ "Володимирська гірка" : "27830351", "Хрещатий парк" : "30356317", "Парк Перемоги" : "23705293", "Володимирська гірка" : "30356317" },"count":3137},{"name":"oleksandrs","paname":{ "Дубовий гай" : "378507377", "Національний природний парк «Голосіївський»" : "630511397", "Парк «Інтернаціональний»" : "37853135", "Національний природний парк «Голосіївський»" : "-421863", "Парк «Юність»" : "37853135", "Бабин Яр" : "-3967863", "Бабин Яр" : "630779811", "Парк «Інтернаціональний»" : "37568873", "Кирилівський гай" : "630779811", "Парк «Нивки»" : "-4178379" },"count":2471},{"name":"truevadila","paname":{ "Золотоворітський сквер" : "27830209", "Гірка Крістера" : "147614036", "Парк Шевченка" : "23581536", "Парк Шевченка" : "444883195", "Парк Кинь-Грусть" : "322958002", "бульвар" : "444883195" },"count":1138},{"name":"westbam","paname":{ "Бабин Яр" : "-3967863", "Бабин Яр" : "630779811", "Парк Перемоги" : "23705293", "Парк «Совки»" : "-5259408", "Сирецький Гай" : "-8885211", "Сирецький Гай" : "-5637222", "Національний природний парк «Голосіївський»" : "-1652168", "Кирилівський гай" : "630779811" },"count":1008},{"name":"mapfool","paname":{ "Наводницький парк" : "30914703", "Печерський ландшафтний парк" : "23709143", "Хрещатий парк" : "30356317", "Старокиївська гора" : "106423651", "Печерський ландшафтний парк" : "30914703", "Ботанічний сад імені Миколи Гришка" : "100352601", "Хрещатий парк" : "474649199", "Хрещатий парк" : "195071759", "Хрещатий парк" : "41079798" },"count":692},{"name":"edwrddp","paname":{ "Веселка" : "232676338", "Дубовий гай" : "378507377", "Парк «Нивки»" : "-4178379", "Парк «Нивки»" : "378507377", "Парк партизанської слави" : "32870085" },"count":479},{"name":"hast","paname":{ "Національний природний парк «Слобожанський»" : "411391910", "Національний природний парк «Слобожанський»" : "-3419143", "Парк-пам'ятка садово-паркового мистецтва «Наталіївський»" : "411391910" },"count":270},{"name":"greyfish","paname":{ "Ботанічний сад «Вінницького національного аграрного університету»" : "-5297702" },"count":173},{"name":"fuser","paname":{ "Ботанічна пам'ятка природи «Будинок вчених»" : "360601183", "Ботанічна памʼятка природи «Сад ім. Т.Г. Шевченка»" : "639438024", "Ботанічна пам'ятка природи «Пушкінська»" : "360601201" },"count":123},{"name":"andergrin","paname":{ "Ботанічна пам'ятка «Кабачок»" : "-6191705" },"count":112}]
